credit_rate_limit/__init__.py
credit_rate_limit/rate_limiter.py
credit_rate_limit-0.2.0.dist-info/LICENSE
credit_rate_limit-0.2.0.dist-info/METADATA
credit_rate_limit-0.2.0.dist-info/WHEEL
credit_rate_limit-0.2.0.dist-info/top_level.txt
credit_rate_limit-0.2.0.dist-info/RECORD
