Metadata-Version: 2.1
Name: credit-rate-limit
Version: 0.2.0
Summary: Easily rate limit async requests to API using credits, computation unit per second (CUPS) or request units, and to those just counting the number of requests per time unit
Author-email: Elnaril <elnaril_dev@caramail.com>
License: MIT License
Project-URL: Homepage, https://github.com/Elnaril/credit-rate-limit
Project-URL: Bug Tracker, https://github.com/Elnaril/credit-rate-limit/issues
Project-URL: Fiverr, https://www.fiverr.com/freelancers/elnaril
Project-URL: Buy Me A Coffee, https://www.buymeacoffee.com/elnaril
Project-URL: Malt, https://www.malt.com/profile/elnaril
Keywords: rate limit,rate limiter,rate-limit,rate-limiter,ratelimit,ratelimiter,throttler,API,decorator,asynchronous,async
Classifier: Development Status :: 2 - Pre-Alpha
Classifier: Intended Audience :: Developers
Classifier: License :: OSI Approved :: MIT License
Classifier: Natural Language :: English
Classifier: Programming Language :: Python :: 3
Classifier: Programming Language :: Python :: 3.8
Classifier: Programming Language :: Python :: 3.9
Classifier: Programming Language :: Python :: 3.10
Classifier: Programming Language :: Python :: 3.11
Classifier: Programming Language :: Python :: 3.12
Classifier: Programming Language :: Python :: 3.13
Classifier: Operating System :: OS Independent
Requires-Python: >=3.8
License-File: LICENSE
